AUTHORS.rst
CHANGELOG.rst
CONTRIBUTING.rst
LICENSE
MAINTAINERS.rst
README.rst
SECURITY.rst
gstore/__init__.py
gstore/__main__.py
gstore/args.py
gstore/cli.py
gstore/client.py
gstore/env.py
gstore/exceptions.py
gstore/logger.py
gstore/models.py
gstore/repo.py
gstore-0.7.0.dist-info/AUTHORS.rst
gstore-0.7.0.dist-info/LICENSE
gstore-0.7.0.dist-info/METADATA
gstore-0.7.0.dist-info/WHEEL
gstore-0.7.0.dist-info/entry_points.txt
gstore-0.7.0.dist-info/RECORD
