Metadata-Version: 2.1
Name: gstore
Version: 0.7.0
Summary: Synchronize GitHub repositories made easy.
Home-page: https://gstore.readthedocs.io
License: GPL-3.0-or-later
Keywords: git,github,backup,repo,sync,cli
Author: Serghei Iakovlev
Author-email: gnu@serghei.pl
Maintainer: Serghei Iakovlev
Maintainer-email: gnu@serghei.pl
Requires-Python: >=3.9,<4
Classifier: Development Status :: 5 - Production/Stable
Classifier: Environment :: Console
Classifier: Intended Audience :: Developers
Classifier: Intended Audience :: Information Technology
Classifier: Intended Audience :: System Administrators
Classifier: License :: OSI Approved :: GNU General Public License v3 or later (GPLv3+)
Classifier: Natural Language :: English
Classifier: Operating System :: OS Independent
Classifier: Programming Language :: Python
Classifier: Programming Language :: Python :: 3
Classifier: Programming Language :: Python :: 3.9
Classifier: Programming Language :: Python :: 3.10
Classifier: Programming Language :: Python :: 3.11
Classifier: Programming Language :: Python :: 3.12
Classifier: Programming Language :: Python :: 3.13
Classifier: Programming Language :: Python :: 3 :: Only
Classifier: Topic :: Software Development :: Build Tools
Classifier: Topic :: Software Development :: Version Control
Classifier: Topic :: Software Development :: Version Control :: Git
Classifier: Topic :: System :: Archiving :: Backup
Classifier: Topic :: System :: Software Distribution
Requires-Dist: gitpython (>=3.1.31,<4.0.0)
Requires-Dist: pygithub (>=2.5.0,<3.0.0)
Project-URL: Bug Tracker, https://github.com/python-poetry/poetry/issues
Project-URL: Changelog, https://gstore.readthedocs.io/en/latest/changelog.html
Project-URL: Documentation, https://gstore.readthedocs.io
Project-URL: Repository, https://github.com/sergeyklay/gstore
